{
  "updated": "2026-06-11T21:09:34.759Z",
  "updated_ru": "11 懈褞薪褟 2026, 21:09 GMT",
  "price": {
    "rate": "1.15370",
    "change": "+0.0004",
    "change_pct": "+0.03",
    "direction": "up",
    "open": "1.1500",
    "high": "1.1555",
    "low": "1.1490",
    "range_pp": 65,
    "source": "ECB/Frankfurter"
  },
  "volatility": {
    "range_pp": 65,
    "level": "脨聮脩聥脩聛脨戮脨潞脨掳脩聫",
    "atr_pct": 93,
    "color": "red"
  },
  "sentiment": {
    "bull": 42,
    "bear": 58,
    "note": "脨聻脩聛脩聜脨戮脩聙脨戮脨露脨陆脩聥脨鹿 脨戮脨驴脩聜脨赂脨录脨赂脨路脨录 芒聙聰 脨聸脨掳脨鲁脨掳脩聙脨麓 脨戮脩聜脨潞脩聙脩聥脨禄脨掳 脨麓脨虏脨碌脩聙脩聦 脨麓脨禄脩聫 2-脨鲁脨戮 脩聟脨掳脨鹿脨潞脨掳, 脨陆脨戮 脨鲁脨碌脨戮脨驴脨戮脨禄脨赂脩聜脨赂脨潞脨掳 脨麓脨掳脨虏脨赂脩聜"
  },
  "news": [
    {
      "src": "ING/FXStreet",
      "time": "脨聼脨戮脩聛脨禄脨碌 ECB",
      "impact": "HIGH",
      "title": "脨聲脨娄脨聭 +25脨卤脨驴 脨麓脨戮 2.25% 芒聙聰 脨赂脩聜脨戮脨鲁脨赂 脨虏脩聡脨碌脩聙脨掳脩聢脨陆脨碌脨鲁脨戮 脨路脨掳脩聛脨碌脨麓脨掳脨陆脨赂脩聫. 脨聸脨掳脨鲁脨掳脩聙脨麓: no pre-set path, 脨陆脨戮 脨虏脩聜脨戮脩聙脨戮脨鹿 脩聟脨掳脨鹿脨潞 脩聛脩聜脨掳脨陆脨戮脨虏脨赂脩聜脩聛脩聫 脨卤脨戮脨禄脨碌脨碌 脨虏脨碌脩聙脨戮脩聫脩聜脨陆脩聥脨录.",
      "move": "芒聠聭 EUR 脩聛脩聙脨碌脨麓脨陆脨碌脩聛脩聙脨戮脩聡脨陆脨戮 芒聙聰 脩聙脩聥脨陆脨潞脨赂 脨路脨掳脨潞脨禄脨掳脨麓脩聥脨虏脨掳脩聨脩聜 脨碌脩聣脩聭 脨戮脨麓脨赂脨陆 脩聟脨掳脨鹿脨潞 脨潞 脩聛脨碌脨陆脩聜脩聫脨卤脩聙脩聨",
      "dir": "up"
    },
    {
      "src": "Reuters",
      "time": "脨拢脩聜脩聙脨戮",
      "impact": "HIGH",
      "title": "脨垄脩聙脨掳脨录脨驴: 脨聵脩聙脨掳脨陆 脨驴脨禄脨掳脩聜脨赂脩聜 脩聛脨禄脨赂脩聢脨潞脨戮脨录 脨麓脨戮脨禄脨鲁脨戮 脨路脨掳 脨录脨赂脩聙. 脨聵脩聙脨掳脨陆脩聛脨潞脨赂脨鹿 脨驴脨掳脩聙脨禄脨掳脨录脨碌脨陆脩聜 脨戮脨卤脨碌脩聣脨掳脨碌脩聜 脩聙脨碌脩聢脨赂脩聜脨碌脨禄脩聦脨陆脩聥脨鹿 脨戮脩聜脨虏脨碌脩聜. 脨聻脩聙脨录脩聝脨路脩聛脨潞脨赂脨鹿 脨驴脩聙脨戮脨禄脨赂脨虏 脨路脨掳脨潞脩聙脩聥脩聜.",
      "move": "芒聠聯 USD 脨麓脨戮脨录脨赂脨陆脨赂脩聙脩聝脨碌脩聜 脨陆脨掳 脨鲁脨碌脨戮脨驴脨戮脨禄脨赂脩聜脨赂脩聡脨碌脩聛脨潞脨戮脨录 脩聙脨赂脩聛脨潞-脨戮脩聞脩聞",
      "dir": "down"
    },
    {
      "src": "FXStreet",
      "time": "脨聮脩聡脨碌脩聙脨掳",
      "impact": "MED",
      "title": "US PPI 脨录脨掳脨鹿: 6.5% 脨鲁/脨鲁 芒聙聰 脨虏脩聥脩聢脨碌 脨驴脩聙脨戮脨鲁脨陆脨戮脨路脨掳 6.1%. 脨陇脨聽脨隆 脨拢脨戮脩聙脩聢 脨陆脨碌 脩聛脨驴脨碌脩聢脨赂脩聜 脩聛脨陆脨赂脨露脨掳脩聜脩聦 脩聛脩聜脨掳脨虏脨潞脨赂.",
      "move": "芒聠聮 脨陆脨碌脨鹿脩聜脩聙脨掳脨禄脩聦脨陆脨戮 脨潞脩聙脨掳脩聜脨潞脨戮脩聛脩聙脨戮脩聡脨陆脨戮, 芒聠聭 EUR 脩聛脩聙脨碌脨麓脨陆脨碌脩聛脩聙脨戮脩聡脨陆脨戮",
      "dir": "neutral"
    },
    {
      "src": "StoneX",
      "time": "脨聬脨陆脨掳脨禄脨赂脨路",
      "impact": "MED",
      "title": "脨隆脨碌脨路脨戮脨陆脨陆脨戮脩聛脩聜脩聦: 脨赂脩聨脨陆脩聦 芒聙聰 3-脨鹿 脩聛脨赂脨禄脩聦脨陆脨碌脨鹿脩聢脨赂脨鹿 脨录脨碌脩聛脩聫脩聠 脨麓脨禄脩聫 EUR/USD (+0.5% avg). 脨聰脨禄脩聫 脩聙脨掳脨禄脨禄脨赂 脨潞 1.18+ 脨陆脩聝脨露脨碌脨陆 脨驴脩聙脨戮脨鲁脩聙脨碌脩聛脩聛 脨虏 脨驴脨碌脩聙脨碌脨鲁脨戮脨虏脨戮脩聙脨掳脩聟.",
      "move": "芒聠聭 脩聛脩聙脨碌脨麓脨陆脨碌脩聛脩聙脨戮脩聡脨陆脩聥脨鹿 脨驴脨戮脩聜脨碌脨陆脩聠脨赂脨掳脨禄 脨驴脩聙脨赂 脨麓脨碌脩聧脩聛脨潞脨掳脨禄脨掳脩聠脨赂脨赂",
      "dir": "up"
    },
    {
      "src": "TradingEconomics",
      "time": "脨垄脨碌脨潞脩聝脩聣脨赂脨鹿",
      "impact": "LOW",
      "title": "EUR/USD 脩聛脩聜脨掳脨卤脨赂脨禄脨赂脨路脨赂脩聙脨戮脨虏脨掳脨禄脩聛脩聫 脩聝 1.154 芒聙聰 脨虏脨卤脨禄脨赂脨路脨赂 2-脨录脨碌脩聛脩聫脩聡脨陆脩聥脩聟 脨录脨赂脨陆脨赂脨录脩聝脨录脨戮脨虏. 脨職脨戮脨陆脩聛脨戮脨禄脨赂脨麓脨掳脩聠脨赂脩聫 脨驴脨戮脩聛脨禄脨碌 ECB 脩聙脨碌脩聢脨碌脨陆脨赂脩聫.",
      "move": "芒聠聮 脨潞脨戮脨陆脩聛脨戮脨禄脨赂脨麓脨掳脩聠脨赂脩聫 1.1490-1.1560",
      "dir": "neutral"
    }
  ],
  "drivers": [
    {
      "label": "冒聼聯聢 脨聲脨娄脨聭 +25脨卤脨驴, 2-脨鹿 脩聟脨掳脨鹿脨潞 脨虏脨碌脩聙脨戮脩聫脩聜脨碌脨陆",
      "type": "bull"
    },
    {
      "label": "冒聼聯聢 脨隆脨碌脨路脨戮脨陆脨陆脨戮脩聛脩聜脩聦 脨赂脩聨脨陆脩聫 脨虏 脨驴脨戮脨禄脩聦脨路脩聝 EUR",
      "type": "bull"
    },
    {
      "label": "冒聼聯聣 脨聻脩聙脨录脩聝脨路 脨路脨掳脨潞脩聙脩聥脩聜, 脨陆脨碌脩聞脩聜脩聦 脨虏脩聥脩聛脨戮脨潞脨戮",
      "type": "bear"
    },
    {
      "label": "冒聼聯聣 脨聵脩聙脨掳脨陆 脨戮脩聜脨虏脨碌脩聙脨鲁 脨驴脨碌脩聙脨碌脨鲁脨戮脨虏脨戮脩聙脩聥",
      "type": "bear"
    },
    {
      "label": "冒聼聯聣 PPI 脨隆脨篓脨聬 6.5% 芒聙聰 脨陇脨聽脨隆 脨麓脨碌脩聙脨露脨赂脩聜",
      "type": "bear"
    },
    {
      "label": "芒職聳 脨職脨戮脨陆脩聛脨戮脨禄脨赂脨麓脨掳脩聠脨赂脩聫 1.1490-1.1560",
      "type": "neutral"
    }
  ],
  "calendar": [
    {
      "time": "08:00",
      "flag": "冒聼聡漏冒聼聡陋",
      "name": "CPI 脨聯脨碌脩聙脨录脨掳脨陆脨赂脩聫 (脩聞脨赂脨陆脨掳脨禄, 脨录脨掳脨鹿)",
      "sub": "脨聼脩聙脨戮脨鲁脨陆脨戮脨路: 2.9% 脨鲁/脨鲁",
      "importance": "med",
      "hot": false
    },
    {
      "time": "12:30",
      "flag": "冒聼聡潞冒聼聡赂",
      "name": "Import Price Index (脨录脨掳脨鹿)",
      "sub": "脨聼脩聙脨戮脨鲁脨陆脨戮脨路: +0.3% 脨录/脨录",
      "importance": "med",
      "hot": false
    },
    {
      "time": "14:00",
      "flag": "冒聼聡潞冒聼聡赂",
      "name": "Michigan Consumer Sentiment",
      "sub": "脨聼脩聙脨戮脨鲁脨陆脨戮脨路: 52.5",
      "importance": "med",
      "hot": false
    },
    {
      "time": "17:00",
      "flag": "冒聼聡潞冒聼聡赂",
      "name": "脨聮脩聥脩聛脩聜脩聝脨驴脨禄脨碌脨陆脨赂脨碌 脨陇脨聽脨隆 脨拢脨戮脩聙脩聢脨掳",
      "sub": "脨隆脨禄脨碌脨麓脨赂脨录 脨路脨掳 脩聛脨赂脨鲁脨陆脨掳脨禄脨掳脨录脨赂 脨驴脨戮 脩聛脩聜脨掳脨虏脨潞脨掳脨录",
      "importance": "high",
      "hot": true
    }
  ],
  "geo": [
    {
      "label": "脨隆脨篓脨聬 脗路 脨聵脩聙脨掳脨陆",
      "status": "脨垄脨拢脨聼脨聵脨職 脨聮 脨聼脨聲脨聽脨聲脨聯脨聻脨聮脨聻脨聽脨聬脨楼",
      "level": "red",
      "title": "冒聼聰麓 脨聵脩聙脨掳脨陆 脨戮脩聜脨虏脨碌脩聙脨鲁 脨录脨赂脩聙脨陆脨戮脨碌 脨驴脩聙脨碌脨麓脨禄脨戮脨露脨碌脨陆脨赂脨碌 脨隆脨篓脨聬",
      "desc": "脨垄脩聙脨掳脨录脨驴 脩聝脨鲁脩聙脨戮脨露脨掳脨碌脩聜 脨陆脨戮脨虏脩聥脨录脨赂 脩聝脨麓脨掳脩聙脨掳脨录脨赂, 脨垄脨碌脨鲁脨碌脩聙脨掳脨陆 脨戮脨卤脨碌脩聣脨掳脨碌脩聜 脨戮脩聜脨虏脨碌脩聜. 脨聻脩聙脨录脩聝脨路脩聛脨潞脨赂脨鹿 脨驴脩聙脨戮脨禄脨赂脨虏 脨路脨掳脨潞脩聙脩聥脩聜 芒聙聰 脨陆脨碌脩聞脩聜脩聦 脨虏脩聥脩聛脨戮脨潞脨掳脩聫, 脨赂脨陆脩聞脨禄脩聫脩聠脨赂脩聫 脨虏 EU 脩聙脨掳脩聛脩聜脩聭脩聜.",
      "dir": "down"
    },
    {
      "label": "脨聵脨路脩聙脨掳脨赂脨禄脩聦 脗路 脨聵脩聙脨掳脨陆",
      "status": "脨聬脨職脨垄脨聵脨聮脨聺脨芦脨聶 脨職脨聻脨聺脨陇脨聸脨聵脨職脨垄",
      "level": "red",
      "title": "冒聼聰麓 脨聻脨卤脨录脨碌脨陆 脩聝脨麓脨掳脩聙脨掳脨录脨赂 脨驴脩聙脨戮脨麓脨戮脨禄脨露脨掳脨碌脩聜脩聛脩聫",
      "desc": "脨聼脨碌脩聙脨碌脨鲁脨戮脨虏脨戮脩聙脩聥 脨戮 脨驴脨碌脩聙脨碌脨录脨赂脩聙脨赂脨赂 脨驴脩聙脨戮脨虏脨掳脨禄脨赂脨禄脨赂脩聛脩聦. 脨聸脩聨脨卤脩聥脨碌 脨陆脨戮脨虏脨戮脩聛脩聜脨赂 脨戮 脨驴脩聙脨碌脨潞脩聙脨掳脩聣脨碌脨陆脨赂脨赂 脨戮脨鲁脨陆脩聫 芒聙聰 脩聛脨赂脨禄脩聦脨陆脩聥脨鹿 脨驴脨戮脨路脨赂脩聜脨赂脨虏 脨麓脨禄脩聫 EUR/USD.",
      "dir": "down"
    },
    {
      "label": "脨聲脨娄脨聭 脗路 脨陇脨聽脨隆",
      "status": "脨聰脨聵脨聮脨聲脨聽脨聯脨聲脨聺脨娄脨聵脨炉 脨隆脨拢脨聳脨聬脨聲脨垄脨隆脨炉",
      "level": "gray",
      "title": "芒職陋 脨聲脨娄脨聭 脩聟脨掳脨鹿脨潞脨掳脨碌脩聜 芒聙聰 脨陇脨聽脨隆 脨露脨麓脩聭脩聜",
      "desc": "脨聲脨娄脨聭 2.25%, 脨陇脨聽脨隆 5.25-5.50%. 脨聰脨赂脩聞脩聞脨碌脩聙脨碌脨陆脩聠脨赂脨掳脨禄 脩聛脩聝脨露脨掳脨碌脩聜脩聛脩聫 芒聙聰 脨麓脨戮脨禄脨鲁脨戮脩聛脩聙脨戮脩聡脨陆脨戮 脨驴脨戮脨麓脨麓脨碌脩聙脨露脨赂脨虏脨掳脨碌脩聜 EUR.",
      "dir": "up"
    }
  ],
  "levels": [
    {
      "tag": "R2",
      "price": "1.1650-1.1680",
      "note": "脨隆脨赂脨禄脩聦脨陆脨戮脨碌 脩聛脨戮脨驴脩聙脨戮脩聜脨赂脨虏脨禄脨碌脨陆脨赂脨碌"
    },
    {
      "tag": "R1",
      "price": "1.1555-1.1580",
      "note": "脨聭脨禄脨赂脨露脨掳脨鹿脩聢脨碌脨碌 脩聛脨戮脨驴脩聙脨戮脩聜脨赂脨虏脨禄脨碌脨陆脨赂脨碌"
    },
    {
      "tag": "NOW",
      "price": "1.1539",
      "note": "脨垄脨碌脨潞脩聝脩聣脨掳脩聫",
      "current": true
    },
    {
      "tag": "S1",
      "price": "1.1490-1.1500",
      "note": "脨聼脩聛脨赂脩聟脨戮脨禄. 脨驴脨戮脨麓脨麓脨碌脩聙脨露脨潞脨掳"
    },
    {
      "tag": "S2",
      "price": "1.1425-1.1450",
      "note": "脨娄脨碌脨禄脩聦 脨录脨碌脨麓脨虏脨碌脨麓脨碌脨鹿"
    }
  ],
  "ai_summary": "EUR/USD 脨潞脨戮脨陆脩聛脨戮脨禄脨赂脨麓脨赂脩聙脩聝脨碌脩聜脩聛脩聫 脩聝 1.1539 脨驴脨戮脩聛脨禄脨碌 脨虏脨戮脨禄脨掳脩聜脨赂脨禄脩聦脨陆脨戮脨鲁脨戮 脩聡脨碌脩聜脨虏脨碌脩聙脨鲁脨掳: 脨聲脨娄脨聭 脨驴脨戮脨麓脨陆脩聫脨禄 脩聛脩聜脨掳脨虏脨潞脩聝 脨麓脨戮 2.25%, 脨陆脨戮 脨碌脨虏脩聙脨戮 脨陆脨碌 脨虏脩聥脩聙脨戮脩聛 脨赂脨路-脨路脨掳 脨鲁脨碌脨戮脨驴脨戮脨禄脨赂脩聜脨赂脩聡脨碌脩聛脨潞脨戮脨鲁脨戮 脩聙脨赂脩聛脨潞-脨戮脩聞脩聞脨掳. 脨隆脨碌脨鲁脨戮脨麓脨陆脩聫 脨鲁脨禄脨掳脨虏脨陆脨戮脨碌 芒聙聰 脨虏脩聥脩聛脩聜脩聝脨驴脨禄脨碌脨陆脨赂脨碌 脨陇脨聽脨隆 脨拢脨戮脩聙脩聢脨掳 脨虏 17:00 GMT. 脨職脩聙脨掳脩聜脨潞脨戮脩聛脩聙脨戮脩聡脨陆脨戮 脨驴脨掳脩聙脨掳 脨虏 脨麓脨赂脨掳脨驴脨掳脨路脨戮脨陆脨碌 1.1490-1.1560."
}