{
  "updated": "2026-06-12T21:00:00Z",
  "updated_ru": "12 июня 2026, 21:00 GMT",
  "price": {
    "rate": "1.1553",
    "change": "+0.0018",
    "change_pct": "+0.16",
    "direction": "up",
    "open": "1.1535",
    "high": "1.1555",
    "low": "1.1526",
    "range_pp": 29,
    "source": "LongForecast/ECB"
  },
  "volatility": {
    "range_pp": 29,
    "level": "Низкая",
    "atr_pct": 41,
    "color": "green"
  },
  "sentiment": {
    "bull": 45,
    "bear": 55,
    "note": "Осторожный оптимизм — EUR отскочил от минимумов, но геополитика сдерживает"
  },
  "news": [
    {
      "src": "LongForecast",
      "time": "Пятница",
      "impact": "HIGH",
      "title": "EUR/USD отскочил от минимумов до 1.1553 (+0.16%). Пара нашла поддержку на макро-уровне 1.1520.",
      "move": "↑ EUR отскок от 2-мес. минимумов",
      "dir": "up"
    },
    {
      "src": "UofM",
      "time": "14:00 GMT",
      "impact": "HIGH",
      "title": "Michigan Consumer Sentiment предв. июнь. Май = 44.8 — рекордный минимум. 57% потребителей жалуются на цены.",
      "move": "↓ слабый сентимент может давить на USD",
      "dir": "up"
    },
    {
      "src": "Kiplinger",
      "time": "Сегодня",
      "impact": "MED",
      "title": "ФРС Уорш: снижение ставок off the table, но и повышение маловероятно до выборов.",
      "move": "→ нейтрально для EUR/USD",
      "dir": "neutral"
    },
    {
      "src": "ForexFactory",
      "time": "След. неделя",
      "impact": "HIGH",
      "title": "Супер-неделя ЦБ: BoJ 16/06, Fed 17/06, BoE 18/06. Главный триггер — решение ФРС 17 июня.",
      "move": "↑ если ФРС довиш, EUR/USD к 1.16+",
      "dir": "up"
    },
    {
      "src": "TradingView",
      "time": "Тех. анализ",
      "impact": "MED",
      "title": "EUR/USD на макро-полу 1.1520. RSI=37 — перепроданность. Поддержка 1.1560, сопрот. 1.1820.",
      "move": "↑ отскок вероятен при RSI<40",
      "dir": "up"
    }
  ],
  "drivers": [
    {
      "label": "📈 ЕЦБ 2.25%, 2-й хайк вероятен",
      "type": "bull"
    },
    {
      "label": "📈 RSI=37 перепроданность",
      "type": "bull"
    },
    {
      "label": "📈 Супер-неделя ЦБ: BoJ+Fed+BoE",
      "type": "bull"
    },
    {
      "label": "📉 Ормуз закрыт, нефть высоко",
      "type": "bear"
    },
    {
      "label": "📉 Потреб. сентимент США на дне",
      "type": "bear"
    },
    {
      "label": "⚖ ФРС on hold до выборов",
      "type": "neutral"
    }
  ],
  "calendar": [
    {
      "time": "14:00",
      "flag": "🇺🇸",
      "name": "Michigan Consumer Sentiment (предв. июнь)",
      "sub": "Май=44.8 рекордный мин. Прогноз: ~46",
      "importance": "high",
      "hot": true
    },
    {
      "time": "16 июня",
      "flag": "🇯🇵",
      "name": "Bank of Japan решение",
      "sub": "Понедельник — влияет на USD/JPY и косвенно EUR",
      "importance": "high",
      "hot": true
    },
    {
      "time": "17 июня",
      "flag": "🇺🇸",
      "name": "Fed решение по ставке",
      "sub": "ГЛАВНОЕ событие недели",
      "importance": "high",
      "hot": true
    },
    {
      "time": "18 июня",
      "flag": "🇬🇧",
      "name": "Bank of England решение",
      "sub": "Влияет на GBP/USD и EUR/GBP",
      "importance": "med",
      "hot": false
    }
  ],
  "geo": [
    {
      "label": "США · Иран",
      "status": "ТУПИК",
      "level": "red",
      "title": "🔴 Ормузский пролив закрыт",
      "desc": "Переговоры в тупике. Бензин дорогой — 57% американцев жалуются на цены. Любой прорыв в переговорах = EUR/USD +200 пп.",
      "dir": "down"
    },
    {
      "label": "ЦБ супер-неделя",
      "status": "ОЖИДАНИЕ",
      "level": "orange",
      "title": "🟡 BoJ + Fed + BoE: три решения за 3 дня",
      "desc": "16-18 июня — 3 центробанка подряд. Если ФРС намекнёт на снижение — EUR/USD к 1.16+. Если ястребиный — к 1.14.",
      "dir": "neutral"
    },
    {
      "label": "ЕЦБ · ФРС",
      "status": "СУЖЕНИЕ",
      "level": "gray",
      "title": "⚪ Дифференциал сужается",
      "desc": "ЕЦБ 2.25% и растёт, ФРС 5.25% и держит. Долгосрочно поддерживает EUR.",
      "dir": "up"
    }
  ],
  "levels": [
    {
      "tag": "R2",
      "price": "1.1660-1.1680",
      "note": "Сильное сопрот."
    },
    {
      "tag": "R1",
      "price": "1.1560-1.1580",
      "note": "Ближ. сопрот."
    },
    {
      "tag": "NOW",
      "price": "1.1553",
      "note": "Текущая",
      "current": true
    },
    {
      "tag": "S1",
      "price": "1.1520-1.1526",
      "note": "Макро-пол"
    },
    {
      "tag": "S2",
      "price": "1.1425-1.1450",
      "note": "Цель медведей"
    }
  ],
  "ai_summary": "EUR/USD закрывает пятницу у 1.1553 (+0.16%), отскочив от макро-пола 1.1520. Волатильность снизилась после вчерашнего шторма вокруг ЕЦБ. Главное на след. неделе — супер-неделя ЦБ: BoJ (пн), Fed (вт), BoE (ср). Решение ФРС 17 июня — ключевой триггер. Michigan Sentiment на дне (44.8) — потребители давят на ФРС."
}